beeflow/__init__.py
beeflow/client/README.md
beeflow/client/__init__.py
beeflow/client/bee_client.py
beeflow/client/core.py
beeflow/cloud_launcher.py
beeflow/common/README.md
beeflow/common/__init__.py
beeflow/common/api.py
beeflow/common/build/README.md
beeflow/common/build/__init__.py
beeflow/common/build/build_driver.py
beeflow/common/build/container_drivers.py
beeflow/common/build/utils.py
beeflow/common/build_interfaces.py
beeflow/common/cli.py
beeflow/common/cli_connection.py
beeflow/common/cloud/README.md
beeflow/common/cloud/__init__.py
beeflow/common/cloud/chameleoncloud.py
beeflow/common/cloud/cloud.py
beeflow/common/cloud/constants.py
beeflow/common/cloud/google.py
beeflow/common/cloud/openstack.py
beeflow/common/cloud/provider.py
beeflow/common/config_driver.py
beeflow/common/config_utils.py
beeflow/common/config_validator.py
beeflow/common/connection.py
beeflow/common/container_path.py
beeflow/common/crt/__init__.py
beeflow/common/crt/charliecloud_driver.py
beeflow/common/crt/crt_driver.py
beeflow/common/crt/singularity_driver.py
beeflow/common/crt_interface.py
beeflow/common/cwl/__init__.py
beeflow/common/cwl/cwl.py
beeflow/common/cwl/examples/Dockerfile.comd-x86_64
beeflow/common/cwl/examples/README.txt
beeflow/common/cwl/examples/cat_grep_tar.py
beeflow/common/cwl/examples/comd.py
beeflow/common/cwl/examples/comd_driver.py
beeflow/common/cwl/examples/comd_pre.sh
beeflow/common/cwl/examples/lorem.txt
beeflow/common/cwl/workflow.py
beeflow/common/db/__init__.py
beeflow/common/db/bdb.py
beeflow/common/db/client_db.py
beeflow/common/db/sched_db.py
beeflow/common/db/tm_db.py
beeflow/common/db/wfm_db.py
beeflow/common/deps/__init__.py
beeflow/common/deps/celery_manager.py
beeflow/common/deps/container_manager.py
beeflow/common/deps/neo4j_manager.py
beeflow/common/deps/redis_manager.py
beeflow/common/expr.py
beeflow/common/gdb/DESIGN.md
beeflow/common/gdb/__init__.py
beeflow/common/gdb/gdb_driver.py
beeflow/common/gdb/generate_graph.py
hpc_beeflow-0.1.10.dist-info/LICENSE
hpc_beeflow-0.1.10.dist-info/METADATA
hpc_beeflow-0.1.10.dist-info/WHEEL
hpc_beeflow-0.1.10.dist-info/entry_points.txt
hpc_beeflow-0.1.10.dist-info/RECORD
