Metadata-Version: 2.3
Name: hpc-beeflow
Version: 0.1.10
Summary: A software package for containerizing HPC applications and managing job workflows
Keywords: bee,hpc,workflow,cluster,computing
Author: BEE-LANL Dev Team
Author-email: bee-dev@lanl.gov
Requires-Python: >=3.8.3,<=3.13.0
Classifier: Environment :: Console
Classifier: Environment :: OpenStack
Classifier: Environment :: Other Environment
Classifier: Intended Audience :: Developers
Classifier: Intended Audience :: Science/Research
Classifier: License :: Other/Proprietary License
Classifier: Natural Language :: English
Classifier: Operating System :: OS Independent
Classifier: Programming Language :: Python :: 3
Classifier: Programming Language :: Python :: 3.9
Classifier: Programming Language :: Python :: 3.10
Classifier: Programming Language :: Python :: 3.11
Classifier: Programming Language :: Python :: 3.12
Classifier: Programming Language :: Python :: 3.13
Classifier: Programming Language :: Python :: Implementation :: CPython
Classifier: Topic :: Scientific/Engineering
Classifier: Topic :: System :: Clustering
Classifier: Topic :: System :: Distributed Computing
Classifier: Topic :: System :: Logging
Classifier: Topic :: System :: Monitoring
Provides-Extra: cloud-extras
Requires-Dist: APScheduler (>=3.6.3,<4.0.0)
Requires-Dist: Flask (>=2.0,<3.0)
Requires-Dist: PyYAML (>=6.0.1,<7.0.0)
Requires-Dist: celery[redis,sqlalchemy] (>=5.3.4,<6.0.0)
Requires-Dist: cffi (>=1.15.1,<2.0.0)
Requires-Dist: cwl-utils (>=0.16,<0.17)
Requires-Dist: docutils (==0.18.1)
Requires-Dist: fastapi (==0.109.2)
Requires-Dist: flask_restful (==0.3.9)
Requires-Dist: google-api-python-client (>=2.66.0,<3.0.0) ; extra == "cloud-extras"
Requires-Dist: graphviz (>=0.20.3,<0.21.0)
Requires-Dist: gunicorn (>=20.1,<23.0)
Requires-Dist: jsonpickle (>=2.2.0,<3.0.0)
Requires-Dist: neo4j (>=5,<6)
Requires-Dist: networkx (==3.1)
Requires-Dist: pre-commit (==3.5.0)
Requires-Dist: pylint (==3.2.7)
Requires-Dist: python-daemon (>=2.3.1,<3.0.0)
Requires-Dist: python-heatclient (>=3.1.0,<4.0.0) ; extra == "cloud-extras"
Requires-Dist: python-openstackclient (>=6.0.0,<7.0.0) ; extra == "cloud-extras"
Requires-Dist: requests (>=2.32.3,<3.0.0)
Requires-Dist: requests-unixsocket2 (>=0.4.2,<0.5.0)
Requires-Dist: typer (>=0.5.0,<0.6.0)
Requires-Dist: uvicorn (==0.27.1)
Project-URL: Repository, https://github.com/lanl/BEE
